pdf_extractor/__init__.py
pdf_extractor/_prompt.py
pdf_extractor/extractor.py
pdf_extractor/parser.py
pdf_extractor/token_fetcher.py
pdf_extractor/uploader.py
pdf_json_extractor/__init__.py
pdf_json_extractor/_prompt.py
pdf_json_extractor/extractor.py
pdf_json_extractor/parser.py
pdf_json_extractor/token_fetcher.py
pdf_json_extractor/uploader.py
pdf_json_extractor-4.5.0.dist-info/METADATA
pdf_json_extractor-4.5.0.dist-info/WHEEL
pdf_json_extractor-4.5.0.dist-info/top_level.txt
pdf_json_extractor-4.5.0.dist-info/RECORD
