Metadata-Version: 2.1
Name: pdf_json_extractor
Version: 4.5.0
Summary: PDF to JSON extractor
Author: RameshLanke
Classifier: Programming Language :: Python :: 3
Classifier: Operating System :: OS Independent
Requires-Python: >=3.7
Requires-Dist: google-generativeai
Requires-Dist: requests
Requires-Dist: beautifulsoup4
